.gitignore
README.md
segmentation_figure.png
setup.py
vdst_toolbox/__init__.py
vdst_toolbox.egg-info/PKG-INFO
vdst_toolbox.egg-info/SOURCES.txt
vdst_toolbox.egg-info/dependency_links.txt
vdst_toolbox.egg-info/requires.txt
vdst_toolbox.egg-info/top_level.txt
vdst_toolbox/descriptive/__init__.py
vdst_toolbox/descriptive/descriptive_function.py
vdst_toolbox/visualizations/__init__.py
vdst_toolbox/visualizations/radar.py