Metadata-Version: 2.1
Name: vdst-toolbox
Version: 1.0.3
Summary: Python package for various tools that will be used by Vestel Team
Home-page: https://github.com/berkaygkv/vdst-toolbox
Author: Berkay Gokova
Author-email: berkaygokova@gmail.com
License: UNKNOWN
Download-URL: https://github.com/berkaygkv/vdst-toolbox/archive/refs/tags/1.0.3.tar.gz
Keywords: python,first package
Platform: UNKNOWN
Classifier: Development Status :: 3 - Alpha
Classifier: Intended Audience :: Education
Classifier: Programming Language :: Python :: 2
Classifier: Programming Language :: Python :: 3
Classifier: Operating System :: MacOS :: MacOS X
Classifier: Operating System :: Microsoft :: Windows
